setup.cfg
setup.py
bin/hko_weather
hko_weather/__init__.py
hko_weather.egg-info/PKG-INFO
hko_weather.egg-info/SOURCES.txt
hko_weather.egg-info/dependency_links.txt
hko_weather.egg-info/requires.txt
hko_weather.egg-info/top_level.txt
hko_weather/models/__init__.py