Metadata-Version: 1.1
Name: hko-weather
Version: 0.1.1
Summary: A HKO Weather Library
Home-page: https://github.com/nickshek/hko_weather
Author: Nick Shek
Author-email: alfshek@hotmail.com
License: MIT
Download-URL: https://github.com/nickshek/hko_weather/archive/0.1.tar.gz
Keywords: HKO,Weather
Platform: UNKNOWN
Classifier: Development Status :: 3 - Alpha
Classifier: License :: OSI Approved :: MIT License
Classifier: Programming Language :: Python :: 3.5
